{"namedChunkGroups":{"polyfill":{"name":"polyfill","assets":[{"name":"webpack-runtime-a348b92d970236293ff7.js","size":5666},{"name":"polyfill-822d76bcd265ddbea6e2.js","size":82527}],"filteredAssets":0,"assetsSize":88193,"filteredAuxiliaryAssets":2,"auxiliaryAssetsSize":221156},"app":{"name":"app","assets":[{"name":"webpack-runtime-a348b92d970236293ff7.js","size":5666},{"name":"styles.acf0267a79280b8ac93c.css","size":556180},{"name":"framework-20f591dbaa94082e9641.js","size":22602},{"name":"ff106bf9-c80fbb1d6f10cbe89308.js","size":9149},{"name":"bca8bde3-f7a8a07bc2be954a3eb0.js","size":15273},{"name":"app-bf8b872f6761dc216a78.js","size":197573}],"filteredAssets":0,"assetsSize":806443,"filteredAuxiliaryAssets":5,"auxiliaryAssetsSize":903615},"component---node-modules-adobe-gatsby-theme-aio-src-pages-404-md":{"name":"component---node-modules-adobe-gatsby-theme-aio-src-pages-404-md","assets":[{"name":"styles.acf0267a79280b8ac93c.css","size":556180},{"name":"b6f3ea4c-223c2f38bb3ae253532f.js","size":7188},{"name":"f5cc1685-39d7ff07aeab9edfafa3.js","size":6078},{"name":"8b61fb39-36b6d0c9dd688eeec35e.js","size":6901},{"name":"7deef1cd-a5b9a274b92f2c39899b.js","size":5633},{"name":"5e65052d-84132b01e6de39698fce.js","size":7005},{"name":"2dee68d8-d47d07b86f20eb595486.js","size":6584},{"name":"commons-647eccb0965cc31b3fce.js","size":102319},{"name":"component---node-modules-adobe-gatsby-theme-aio-src-pages-404-md-efe1fd4268cbb0d6323b.js","size":1102}],"filteredAssets":0,"assetsSize":698990,"filteredAuxiliaryAssets":8,"auxiliaryAssetsSize":375968},"component---src-pages-api-index-md":{"name":"component---src-pages-api-index-md","assets":[{"name":"styles.acf0267a79280b8ac93c.css","size":556180},{"name":"b6f3ea4c-223c2f38bb3ae253532f.js","size":7188},{"name":"f5cc1685-39d7ff07aeab9edfafa3.js","size":6078},{"name":"8b61fb39-36b6d0c9dd688eeec35e.js","size":6901},{"name":"7deef1cd-a5b9a274b92f2c39899b.js","size":5633},{"name":"5e65052d-84132b01e6de39698fce.js","size":7005},{"name":"2dee68d8-d47d07b86f20eb595486.js","size":6584},{"name":"commons-647eccb0965cc31b3fce.js","size":102319},{"name":"component---src-pages-api-index-md-3547d93c4f900fcc96ab.js","size":557}],"filteredAssets":0,"assetsSize":698445,"filteredAuxiliaryAssets":8,"auxiliaryAssetsSize":374923},"component---src-pages-code-sample-index-md":{"name":"component---src-pages-code-sample-index-md","assets":[{"name":"styles.acf0267a79280b8ac93c.css","size":556180},{"name":"b6f3ea4c-223c2f38bb3ae253532f.js","size":7188},{"name":"f5cc1685-39d7ff07aeab9edfafa3.js","size":6078},{"name":"8b61fb39-36b6d0c9dd688eeec35e.js","size":6901},{"name":"7deef1cd-a5b9a274b92f2c39899b.js","size":5633},{"name":"5e65052d-84132b01e6de39698fce.js","size":7005},{"name":"2dee68d8-d47d07b86f20eb595486.js","size":6584},{"name":"commons-647eccb0965cc31b3fce.js","size":102319},{"name":"component---src-pages-code-sample-index-md-5ce0dd5c6c87d22d4281.js","size":49940}],"filteredAssets":0,"assetsSize":747828,"filteredAuxiliaryAssets":8,"auxiliaryAssetsSize":433932},"component---src-pages-features-index-md":{"name":"component---src-pages-features-index-md","assets":[{"name":"styles.acf0267a79280b8ac93c.css","size":556180},{"name":"b6f3ea4c-223c2f38bb3ae253532f.js","size":7188},{"name":"f5cc1685-39d7ff07aeab9edfafa3.js","size":6078},{"name":"8b61fb39-36b6d0c9dd688eeec35e.js","size":6901},{"name":"7deef1cd-a5b9a274b92f2c39899b.js","size":5633},{"name":"5e65052d-84132b01e6de39698fce.js","size":7005},{"name":"2dee68d8-d47d07b86f20eb595486.js","size":6584},{"name":"commons-647eccb0965cc31b3fce.js","size":102319},{"name":"component---src-pages-features-index-md-8ec059da15934cae52c9.js","size":29724}],"filteredAssets":0,"assetsSize":727612,"filteredAuxiliaryAssets":8,"auxiliaryAssetsSize":417101},"component---src-pages-features-supported-fonts-index-md":{"name":"component---src-pages-features-supported-fonts-index-md","assets":[{"name":"styles.acf0267a79280b8ac93c.css","size":556180},{"name":"b6f3ea4c-223c2f38bb3ae253532f.js","size":7188},{"name":"f5cc1685-39d7ff07aeab9edfafa3.js","size":6078},{"name":"8b61fb39-36b6d0c9dd688eeec35e.js","size":6901},{"name":"7deef1cd-a5b9a274b92f2c39899b.js","size":5633},{"name":"5e65052d-84132b01e6de39698fce.js","size":7005},{"name":"2dee68d8-d47d07b86f20eb595486.js","size":6584},{"name":"commons-647eccb0965cc31b3fce.js","size":102319},{"name":"component---src-pages-features-supported-fonts-index-md-bd773c93f2cccc699950.js","size":7722}],"filteredAssets":0,"assetsSize":705610,"filteredAuxiliaryAssets":8,"auxiliaryAssetsSize":388963},"component---src-pages-general-workflow-index-md":{"name":"component---src-pages-general-workflow-index-md","assets":[{"name":"styles.acf0267a79280b8ac93c.css","size":556180},{"name":"b6f3ea4c-223c2f38bb3ae253532f.js","size":7188},{"name":"f5cc1685-39d7ff07aeab9edfafa3.js","size":6078},{"name":"8b61fb39-36b6d0c9dd688eeec35e.js","size":6901},{"name":"7deef1cd-a5b9a274b92f2c39899b.js","size":5633},{"name":"5e65052d-84132b01e6de39698fce.js","size":7005},{"name":"2dee68d8-d47d07b86f20eb595486.js","size":6584},{"name":"commons-647eccb0965cc31b3fce.js","size":102319},{"name":"component---src-pages-general-workflow-index-md-5ce510760e61b5facc3c.js","size":3554}],"filteredAssets":0,"assetsSize":701442,"filteredAuxiliaryAssets":8,"auxiliaryAssetsSize":378661},"component---src-pages-getting-started-index-md":{"name":"component---src-pages-getting-started-index-md","assets":[{"name":"styles.acf0267a79280b8ac93c.css","size":556180},{"name":"b6f3ea4c-223c2f38bb3ae253532f.js","size":7188},{"name":"f5cc1685-39d7ff07aeab9edfafa3.js","size":6078},{"name":"8b61fb39-36b6d0c9dd688eeec35e.js","size":6901},{"name":"7deef1cd-a5b9a274b92f2c39899b.js","size":5633},{"name":"5e65052d-84132b01e6de39698fce.js","size":7005},{"name":"2dee68d8-d47d07b86f20eb595486.js","size":6584},{"name":"commons-647eccb0965cc31b3fce.js","size":102319},{"name":"component---src-pages-getting-started-index-md-87baf208f42776fe226c.js","size":6821}],"filteredAssets":0,"assetsSize":704709,"filteredAuxiliaryAssets":8,"auxiliaryAssetsSize":383362},"component---src-pages-index-md":{"name":"component---src-pages-index-md","assets":[{"name":"styles.acf0267a79280b8ac93c.css","size":556180},{"name":"b6f3ea4c-223c2f38bb3ae253532f.js","size":7188},{"name":"f5cc1685-39d7ff07aeab9edfafa3.js","size":6078},{"name":"8b61fb39-36b6d0c9dd688eeec35e.js","size":6901},{"name":"7deef1cd-a5b9a274b92f2c39899b.js","size":5633},{"name":"5e65052d-84132b01e6de39698fce.js","size":7005},{"name":"2dee68d8-d47d07b86f20eb595486.js","size":6584},{"name":"commons-647eccb0965cc31b3fce.js","size":102319},{"name":"component---src-pages-index-md-b2d7f24f418d68a0bc39.js","size":4893}],"filteredAssets":0,"assetsSize":702781,"filteredAuxiliaryAssets":8,"auxiliaryAssetsSize":381693},"component---src-pages-release-notes-index-md":{"name":"component---src-pages-release-notes-index-md","assets":[{"name":"styles.acf0267a79280b8ac93c.css","size":556180},{"name":"b6f3ea4c-223c2f38bb3ae253532f.js","size":7188},{"name":"f5cc1685-39d7ff07aeab9edfafa3.js","size":6078},{"name":"8b61fb39-36b6d0c9dd688eeec35e.js","size":6901},{"name":"7deef1cd-a5b9a274b92f2c39899b.js","size":5633},{"name":"5e65052d-84132b01e6de39698fce.js","size":7005},{"name":"2dee68d8-d47d07b86f20eb595486.js","size":6584},{"name":"commons-647eccb0965cc31b3fce.js","size":102319},{"name":"component---src-pages-release-notes-index-md-e16fbc75b82a0ceb8955.js","size":669}],"filteredAssets":0,"assetsSize":698557,"filteredAuxiliaryAssets":8,"auxiliaryAssetsSize":375093},"component---src-pages-support-index-md":{"name":"component---src-pages-support-index-md","assets":[{"name":"styles.acf0267a79280b8ac93c.css","size":556180},{"name":"b6f3ea4c-223c2f38bb3ae253532f.js","size":7188},{"name":"f5cc1685-39d7ff07aeab9edfafa3.js","size":6078},{"name":"8b61fb39-36b6d0c9dd688eeec35e.js","size":6901},{"name":"7deef1cd-a5b9a274b92f2c39899b.js","size":5633},{"name":"5e65052d-84132b01e6de39698fce.js","size":7005},{"name":"2dee68d8-d47d07b86f20eb595486.js","size":6584},{"name":"commons-647eccb0965cc31b3fce.js","size":102319},{"name":"component---src-pages-support-index-md-39910fe0f31ca4fb1595.js","size":960}],"filteredAssets":0,"assetsSize":698848,"filteredAuxiliaryAssets":8,"auxiliaryAssetsSize":375528}},"assetsByChunkName":{"polyfill":["webpack-runtime-a348b92d970236293ff7.js","polyfill-822d76bcd265ddbea6e2.js"],"app":["webpack-runtime-a348b92d970236293ff7.js","styles.acf0267a79280b8ac93c.css","framework-20f591dbaa94082e9641.js","ff106bf9-c80fbb1d6f10cbe89308.js","bca8bde3-f7a8a07bc2be954a3eb0.js","app-bf8b872f6761dc216a78.js"],"component---node-modules-adobe-gatsby-theme-aio-src-pages-404-md":["styles.acf0267a79280b8ac93c.css","b6f3ea4c-223c2f38bb3ae253532f.js","f5cc1685-39d7ff07aeab9edfafa3.js","8b61fb39-36b6d0c9dd688eeec35e.js","7deef1cd-a5b9a274b92f2c39899b.js","5e65052d-84132b01e6de39698fce.js","2dee68d8-d47d07b86f20eb595486.js","commons-647eccb0965cc31b3fce.js","component---node-modules-adobe-gatsby-theme-aio-src-pages-404-md-efe1fd4268cbb0d6323b.js"],"component---src-pages-api-index-md":["styles.acf0267a79280b8ac93c.css","b6f3ea4c-223c2f38bb3ae253532f.js","f5cc1685-39d7ff07aeab9edfafa3.js","8b61fb39-36b6d0c9dd688eeec35e.js","7deef1cd-a5b9a274b92f2c39899b.js","5e65052d-84132b01e6de39698fce.js","2dee68d8-d47d07b86f20eb595486.js","commons-647eccb0965cc31b3fce.js","component---src-pages-api-index-md-3547d93c4f900fcc96ab.js"],"component---src-pages-code-sample-index-md":["styles.acf0267a79280b8ac93c.css","b6f3ea4c-223c2f38bb3ae253532f.js","f5cc1685-39d7ff07aeab9edfafa3.js","8b61fb39-36b6d0c9dd688eeec35e.js","7deef1cd-a5b9a274b92f2c39899b.js","5e65052d-84132b01e6de39698fce.js","2dee68d8-d47d07b86f20eb595486.js","commons-647eccb0965cc31b3fce.js","component---src-pages-code-sample-index-md-5ce0dd5c6c87d22d4281.js"],"component---src-pages-features-index-md":["styles.acf0267a79280b8ac93c.css","b6f3ea4c-223c2f38bb3ae253532f.js","f5cc1685-39d7ff07aeab9edfafa3.js","8b61fb39-36b6d0c9dd688eeec35e.js","7deef1cd-a5b9a274b92f2c39899b.js","5e65052d-84132b01e6de39698fce.js","2dee68d8-d47d07b86f20eb595486.js","commons-647eccb0965cc31b3fce.js","component---src-pages-features-index-md-8ec059da15934cae52c9.js"],"component---src-pages-features-supported-fonts-index-md":["styles.acf0267a79280b8ac93c.css","b6f3ea4c-223c2f38bb3ae253532f.js","f5cc1685-39d7ff07aeab9edfafa3.js","8b61fb39-36b6d0c9dd688eeec35e.js","7deef1cd-a5b9a274b92f2c39899b.js","5e65052d-84132b01e6de39698fce.js","2dee68d8-d47d07b86f20eb595486.js","commons-647eccb0965cc31b3fce.js","component---src-pages-features-supported-fonts-index-md-bd773c93f2cccc699950.js"],"component---src-pages-general-workflow-index-md":["styles.acf0267a79280b8ac93c.css","b6f3ea4c-223c2f38bb3ae253532f.js","f5cc1685-39d7ff07aeab9edfafa3.js","8b61fb39-36b6d0c9dd688eeec35e.js","7deef1cd-a5b9a274b92f2c39899b.js","5e65052d-84132b01e6de39698fce.js","2dee68d8-d47d07b86f20eb595486.js","commons-647eccb0965cc31b3fce.js","component---src-pages-general-workflow-index-md-5ce510760e61b5facc3c.js"],"component---src-pages-getting-started-index-md":["styles.acf0267a79280b8ac93c.css","b6f3ea4c-223c2f38bb3ae253532f.js","f5cc1685-39d7ff07aeab9edfafa3.js","8b61fb39-36b6d0c9dd688eeec35e.js","7deef1cd-a5b9a274b92f2c39899b.js","5e65052d-84132b01e6de39698fce.js","2dee68d8-d47d07b86f20eb595486.js","commons-647eccb0965cc31b3fce.js","component---src-pages-getting-started-index-md-87baf208f42776fe226c.js"],"component---src-pages-index-md":["styles.acf0267a79280b8ac93c.css","b6f3ea4c-223c2f38bb3ae253532f.js","f5cc1685-39d7ff07aeab9edfafa3.js","8b61fb39-36b6d0c9dd688eeec35e.js","7deef1cd-a5b9a274b92f2c39899b.js","5e65052d-84132b01e6de39698fce.js","2dee68d8-d47d07b86f20eb595486.js","commons-647eccb0965cc31b3fce.js","component---src-pages-index-md-b2d7f24f418d68a0bc39.js"],"component---src-pages-release-notes-index-md":["styles.acf0267a79280b8ac93c.css","b6f3ea4c-223c2f38bb3ae253532f.js","f5cc1685-39d7ff07aeab9edfafa3.js","8b61fb39-36b6d0c9dd688eeec35e.js","7deef1cd-a5b9a274b92f2c39899b.js","5e65052d-84132b01e6de39698fce.js","2dee68d8-d47d07b86f20eb595486.js","commons-647eccb0965cc31b3fce.js","component---src-pages-release-notes-index-md-e16fbc75b82a0ceb8955.js"],"component---src-pages-support-index-md":["styles.acf0267a79280b8ac93c.css","b6f3ea4c-223c2f38bb3ae253532f.js","f5cc1685-39d7ff07aeab9edfafa3.js","8b61fb39-36b6d0c9dd688eeec35e.js","7deef1cd-a5b9a274b92f2c39899b.js","5e65052d-84132b01e6de39698fce.js","2dee68d8-d47d07b86f20eb595486.js","commons-647eccb0965cc31b3fce.js","component---src-pages-support-index-md-39910fe0f31ca4fb1595.js"]},"childAssetsByChunkName":{}}